{
    "songs": [
        {
            "albumart": "https://leo-t-88.github.io/tune-radio/assets/radio/kissfm.png",
            "author": "L'Esprit du Sud",
            "song": "Kiss FM - Cannes, Grasses & Antibes",
            "json": "",
            "audio": "https://kissfmcannes.ice.infomaniak.ch/kissfmcannes-128.mp3"
        },
        {
            "albumart": "https://leo-t-88.github.io/tune-radio/assets/radio/kissfm.png",
            "author": "L'Esprit du Sud",
            "song": "Kiss FM - Est & Centre Var",
            "json": "",
            "audio": "https://kissfmvarest.ice.infomaniak.ch/kissfmvarest-128.mp3"
        },
        {
            "albumart": "https://leo-t-88.github.io/tune-radio/assets/radio/kissfm.png",
            "author": "L'Esprit du Sud",
            "song": "Kiss FM - Nice",
            "json": "",
            "audio": "https://kissfm.ice.infomaniak.ch/kissfm-128.mp3"
        },
        {
            "albumart": "https://leo-t-88.github.io/tune-radio/assets/radio/kissfm.png",
            "author": "L'Esprit du Sud",
            "song": "Kiss FM - Toulon / Marseille",
            "json": "",
            "audio": "https://kissfm2.ice.infomaniak.ch/kissfm2-128.mp3"
        }
    ]
}
